conctl/__init__.py
conctl/base.py
conctl/containerd.py
conctl/docker.py
conctl/bin/conctl.py
conctl-0.1.0.dist-info/LICENSE
conctl-0.1.0.dist-info/METADATA
conctl-0.1.0.dist-info/WHEEL
conctl-0.1.0.dist-info/entry_points.txt
conctl-0.1.0.dist-info/top_level.txt
conctl-0.1.0.dist-info/RECORD
