Metadata-Version: 2.1
Name: conctl
Version: 0.1.0
Summary: Drive Containerd and Docker from one CLI
Home-page: https://github.com/joedborg/conctl
Author: Joe Borg
Author-email: joseph.borg@canonical.com
License: Apache License 2.0
Platform: UNKNOWN
Requires-Dist: click
